novyx_langchain/__init__.py
novyx_langchain/buffer.py
novyx_langchain/checkpointer.py
novyx_langchain/integrity.py
novyx_langchain/memory.py
novyx_langchain-0.1.2.dist-info/licenses/LICENSE
novyx_langchain-0.1.2.dist-info/METADATA
novyx_langchain-0.1.2.dist-info/WHEEL
novyx_langchain-0.1.2.dist-info/top_level.txt
novyx_langchain-0.1.2.dist-info/RECORD
