Metadata-Version: 2.4
Name: novyx-langchain
Version: 0.1.2
Summary: Persistent semantic memory for LangChain agents using Novyx RAM
Author-email: Novyx Labs <hello@novyxlabs.com>
Maintainer-email: Novyx Labs <hello@novyxlabs.com>
License: MIT
Project-URL: Homepage, https://novyxlabs.com/integrations/langchain
Project-URL: Documentation, https://docs.novyxlabs.com/integrations/langchain
Project-URL: Repository, https://github.com/novyxlabs/novyx-langchain
Project-URL: Changelog, https://github.com/novyxlabs/novyx-langchain/blob/main/CHANGELOG.md
Project-URL: Issues, https://github.com/novyxlabs/novyx-langchain/issues
Keywords: langchain,langgraph,memory,ai,agents,llm,persistent,semantic,rag,novyx
Classifier: Development Status :: 4 - Beta
Classifier: Intended Audience :: Developers
Classifier: License :: OSI Approved :: MIT License
Classifier: Operating System :: OS Independent
Classifier: Programming Language :: Python :: 3
Classifier: Programming Language :: Python :: 3.9
Classifier: Programming Language :: Python :: 3.10
Classifier: Programming Language :: Python :: 3.11
Classifier: Programming Language :: Python :: 3.12
Classifier: Topic :: Scientific/Engineering :: Artificial Intelligence
Classifier: Topic :: Software Development :: Libraries :: Python Modules
Requires-Python: >=3.9
License-File: LICENSE
Requires-Dist: requests>=2.28.0
Requires-Dist: pydantic>=2.0.0
Requires-Dist: langchain-core>=0.1.0
Provides-Extra: langgraph
Requires-Dist: langgraph>=0.2.0; extra == "langgraph"
Provides-Extra: integrity
Provides-Extra: all
Requires-Dist: langgraph>=0.2.0; extra == "all"
Provides-Extra: dev
Requires-Dist: pytest>=7.0.0; extra == "dev"
Requires-Dist: pytest-asyncio>=0.21.0; extra == "dev"
Requires-Dist: pytest-cov>=4.0.0; extra == "dev"
Requires-Dist: black>=23.0.0; extra == "dev"
Requires-Dist: ruff>=0.1.0; extra == "dev"
Requires-Dist: mypy>=1.0.0; extra == "dev"
Dynamic: license-file
